{"name":"build-javascript","namedChunkGroups":{"polyfill":{"name":"polyfill","assets":[{"name":"webpack-runtime-07e6ce5d9558bdea68fb.js","size":3187},{"name":"polyfill-e92cacd4bfc38a08c046.js","size":85842}],"filteredAssets":0,"assetsSize":89029,"filteredAuxiliaryAssets":2,"auxiliaryAssetsSize":221147},"app":{"name":"app","assets":[{"name":"webpack-runtime-07e6ce5d9558bdea68fb.js","size":3187},{"name":"framework-dd1332f8f5b0a5b1dd8b.js","size":128701},{"name":"app-279db1d5cb8af6df00dc.js","size":79691}],"filteredAssets":0,"assetsSize":211579,"filteredAuxiliaryAssets":3,"auxiliaryAssetsSize":713319},"component---src-pages-404-js":{"name":"component---src-pages-404-js","assets":[{"name":"component---src-pages-404-js-76ca940efef941f23b71.js","size":757}],"filteredAssets":0,"assetsSize":757,"filteredAuxiliaryAssets":1,"auxiliaryAssetsSize":1867},"component---src-pages-index-js":{"name":"component---src-pages-index-js","assets":[{"name":"component---src-pages-index-js-46adb4a6f00460f7b504.js","size":3851}],"filteredAssets":0,"assetsSize":3851,"filteredAuxiliaryAssets":1,"auxiliaryAssetsSize":7596}},"assetsByChunkName":{"polyfill":["webpack-runtime-07e6ce5d9558bdea68fb.js","polyfill-e92cacd4bfc38a08c046.js"],"app":["webpack-runtime-07e6ce5d9558bdea68fb.js","framework-dd1332f8f5b0a5b1dd8b.js","app-279db1d5cb8af6df00dc.js"],"component---src-pages-404-js":["component---src-pages-404-js-76ca940efef941f23b71.js"],"component---src-pages-index-js":["component---src-pages-index-js-46adb4a6f00460f7b504.js"]},"childAssetsByChunkName":{}}